pyupway/__init__.py
pyupway/config/__init__.py
pyupway/config/myupwayconfig.py
pyupway/enums/__init__.py
pyupway/enums/dataservice.py
pyupway/enums/variable.py
pyupway/exceptions/__init__.py
pyupway/exceptions/configurationerror.py
pyupway/exceptions/loginerror.py
pyupway/exceptions/responseerror.py
pyupway/models/__init__.py
pyupway/models/valuemodel.py
pyupway/models/variablehistoryvalue.py
pyupway/models/variablevalue.py
pyupway/responses/__init__.py
pyupway/responses/myupwayresponses.py
pyupway/services/__init__.py
pyupway/services/myuplinkservice.py
pyupway/services/myupwayservice.py
pyupway-0.0.17.dist-info/METADATA
pyupway-0.0.17.dist-info/WHEEL
pyupway-0.0.17.dist-info/licenses/LICENSE
pyupway-0.0.17.dist-info/RECORD
