Metadata-Version: 2.3
Name: pyupway
Version: 0.0.17
Summary: Read values from MyUpway cloud service
Project-URL: Homepage, https://github.com/lemanjo/pyupway
Project-URL: Changelog, https://github.com/lemanjo/pyupway/blob/master/changelog.md
Author-email: Jussi Rosenberg <jussi.rosenberg@iki.fi>
License-File: LICENSE
Keywords: Heat pump,Jäspi,MyUpway,Nibe
Classifier: License :: OSI Approved :: MIT License
Classifier: Operating System :: OS Independent
Classifier: Programming Language :: Python :: 3
Requires-Python: >=3.8
Requires-Dist: requests>=2.31.0
